Metadata-Version: 2.1
Name: puredb
Version: 2022.3.9.22.40
Summary: 封装自用的leveldb
Home-page: UNKNOWN
Author: chenzongwei
Author-email: 17695480342@163.com
License: MIT
Platform: UNKNOWN
Requires-Python: >=3
License-File: LICENSE
